gimmebio.sample_seqs-0.3.7-py3.8-nspkg.pth
gimmebio/sample_seqs/__init__.py
gimmebio/sample_seqs/constants.py
gimmebio/sample_seqs/sample_seqs.py
gimmebio/sample_seqs/data/README.md
gimmebio/sample_seqs/data/c_acnes.GCF_000008345.1_ASM834v1_feature_table.txt
gimmebio/sample_seqs/data/c_acnes.GCF_000008345.1_ASM834v1_genomic.fna
gimmebio/sample_seqs/data/e_coli.GCF_000005845.2_ASM584v2_feature_table.txt
gimmebio/sample_seqs/data/e_coli.GCF_000005845.2_ASM584v2_genomic.fna
gimmebio/sample_seqs/data/megares_database_v1.01.fasta
gimmebio/sample_seqs/data/sample_fastq_zymo_control.fq
gimmebio.sample_seqs-0.3.7.dist-info/METADATA
gimmebio.sample_seqs-0.3.7.dist-info/WHEEL
gimmebio.sample_seqs-0.3.7.dist-info/namespace_packages.txt
gimmebio.sample_seqs-0.3.7.dist-info/top_level.txt
gimmebio.sample_seqs-0.3.7.dist-info/RECORD
